nucleobench/__init__.py
nucleobench/common/__init__.py
nucleobench/common/argparse_lib.py
nucleobench/common/attribution_lib_torch.py
nucleobench/common/attribution_lib_torch_test.py
nucleobench/common/constants.py
nucleobench/common/gcp_utils.py
nucleobench/common/memory_utils.py
nucleobench/common/priority_queue.py
nucleobench/common/priority_queue_test.py
nucleobench/common/string_utils.py
nucleobench/common/string_utils_test.py
nucleobench/common/testing_utils.py
nucleobench/common/testing_utils_test.py
nucleobench/models/__init__.py
nucleobench/models/bpnet/__init__.py
nucleobench/models/bpnet/constants.py
nucleobench/models/bpnet/load_model.py
nucleobench/models/bpnet/model_def.py
nucleobench/models/bpnet/model_def_test.py
nucleobench/models/dummy/__init__.py
nucleobench/models/dummy/model_def.py
nucleobench/models/grelu/__init__.py
nucleobench/models/grelu/constants.py
nucleobench/models/grelu/constants_test.py
nucleobench/models/grelu/model_def.py
nucleobench/models/grelu/enformer/__init__.py
nucleobench/models/grelu/enformer/constants.py
nucleobench/models/grelu/enformer/model_def.py
nucleobench/models/grelu/enformer/model_def_test.py
nucleobench/models/malinois/__init__.py
nucleobench/models/malinois/load_model.py
nucleobench/models/malinois/model_def.py
nucleobench/models/malinois/model_def_test.py
nucleobench/models/malinois/model/__init__.py
nucleobench/models/malinois/model/basset.py
nucleobench/models/malinois/model/custom_layers.py
nucleobench/models/malinois/model/loss_functions.py
nucleobench/models/malinois/model/utils.py
nucleobench/models/substring_count_net/__init__.py
nucleobench/models/substring_count_net/model_def.py
nucleobench/models/substring_count_net/model_def_test.py
nucleobench/optimizations/__init__.py
nucleobench/optimizations/model_class.py
nucleobench/optimizations/optimization_class.py
nucleobench/optimizations/typing.py
nucleobench/optimizations/utils.py
nucleobench/optimizations/utils_test.py
nucleobench-1.0.4.dist-info/licenses/LICENSE
nucleobench-1.0.4.dist-info/METADATA
nucleobench-1.0.4.dist-info/WHEEL
nucleobench-1.0.4.dist-info/top_level.txt
nucleobench-1.0.4.dist-info/RECORD
